odoo8_addon_l10n_it_fatturapa_in-8.0.2.0.6-py3.8-nspkg.pth
odoo_addons/l10n_it_fatturapa_in/README.rst
odoo_addons/l10n_it_fatturapa_in/__init__.py
odoo_addons/l10n_it_fatturapa_in/__openerp__.py
odoo_addons/l10n_it_fatturapa_in/i18n/it.po
odoo_addons/l10n_it_fatturapa_in/i18n/l10n_it_fatturapa_in.pot
odoo_addons/l10n_it_fatturapa_in/migrations/8.0.1.4.0/post-migration.py
odoo_addons/l10n_it_fatturapa_in/migrations/8.0.1.5.0/post-migration.py
odoo_addons/l10n_it_fatturapa_in/models/__init__.py
odoo_addons/l10n_it_fatturapa_in/models/account.py
odoo_addons/l10n_it_fatturapa_in/models/attachment.py
odoo_addons/l10n_it_fatturapa_in/models/company.py
odoo_addons/l10n_it_fatturapa_in/models/partner.py
odoo_addons/l10n_it_fatturapa_in/readme/CONFIGURE.rst
odoo_addons/l10n_it_fatturapa_in/readme/CONTRIBUTORS.rst
odoo_addons/l10n_it_fatturapa_in/readme/DESCRIPTION.rst
odoo_addons/l10n_it_fatturapa_in/readme/INSTALL.rst
odoo_addons/l10n_it_fatturapa_in/readme/ROADMAP.rst
odoo_addons/l10n_it_fatturapa_in/readme/USAGE.rst
odoo_addons/l10n_it_fatturapa_in/security/ir.model.access.csv
odoo_addons/l10n_it_fatturapa_in/security/rules.xml
odoo_addons/l10n_it_fatturapa_in/static/description/icon.png
odoo_addons/l10n_it_fatturapa_in/static/description/index.html
odoo_addons/l10n_it_fatturapa_in/static/src/img/icon.png
odoo_addons/l10n_it_fatturapa_in/tests/__init__.py
odoo_addons/l10n_it_fatturapa_in/tests/fatturapa_common.py
odoo_addons/l10n_it_fatturapa_in/tests/test_import_fatturapa_xml.py
odoo_addons/l10n_it_fatturapa_in/tests/data/IT01234567890_FPR03.base64.xml.p7m
odoo_addons/l10n_it_fatturapa_in/tests/data/IT01234567890_FPR03.xml
odoo_addons/l10n_it_fatturapa_in/tests/data/IT01234567890_FPR04.base64.xml.p7m
odoo_addons/l10n_it_fatturapa_in/tests/data/IT01234567890_FPR04.xml
odoo_addons/l10n_it_fatturapa_in/tests/data/IT01234567890_FPR05.xml
odoo_addons/l10n_it_fatturapa_in/tests/data/IT01234567890_FPR06.xml
odoo_addons/l10n_it_fatturapa_in/tests/data/IT01234567890_FPR07.xml
odoo8_addon_l10n_it_fatturapa_in-8.0.2.0.6.dist-info/METADATA
odoo8_addon_l10n_it_fatturapa_in-8.0.2.0.6.dist-info/WHEEL
odoo8_addon_l10n_it_fatturapa_in-8.0.2.0.6.dist-info/namespace_packages.txt
odoo8_addon_l10n_it_fatturapa_in-8.0.2.0.6.dist-info/top_level.txt
odoo8_addon_l10n_it_fatturapa_in-8.0.2.0.6.dist-info/RECORD
