Metadata-Version: 2.1
Name: odoo8-addon-l10n-it-fatturapa-in
Version: 8.0.2.0.6
Summary: Electronic invoices reception
Home-page: https://github.com/OCA/l10n-italy/tree/8.0/l10n_it_fatturapa_in
Author: Agile Business Group, Innoviu, Odoo Community Association (OCA)
Author-email: support@odoo-community.org
License: LGPL-3
Platform: UNKNOWN
Classifier: Programming Language :: Python
Classifier: Framework :: Odoo
Classifier: Framework :: Odoo :: 8.0
Classifier: License :: OSI Approved :: GNU Lesser General Public License v3 (LGPLv3)
Classifier: Development Status :: 4 - Beta
Requires-Python: ~=2.7
Requires-Dist: odoo8-addon-l10n-it-fatturapa
Requires-Dist: odoo8-addon-l10n-it-withholding-tax-causali
Requires-Dist: odoo (<9.0a,>=8.0a)
